HDL codes/or_xor_and.v
module OR_XOR_AND_Nbit 
(
    input wire [5:0] A,B,
    output wire [5:0] R
);

    assign R = ((A|B)^(A&B)); 

endmodule

HDL codes/add.v
module ALU_ADD_SUB_Nbit 
(
    input wire [5:0] A,B,  
    output wire [5:0] R,    
    output wire CF
);

    assign {CF, R} = A + B;


endmodule

HDL codes/alu.v
module ALU
(
    input wire [5:0] A, B,                   
    input wire [1:0] OP,    
    output wire [5:0] R,     
    output wire alu_flag          
);

    reg [5:0] result;
    wire [5:0] R_ADD, XOR;
    wire CF_ADD;

    // Instantiate modules
    ALU_ADD_SUB_Nbit  ADD_SUB1(A,B,R_ADD,CF_ADD);

    OR_XOR_AND_Nbit OR_XOR_AND1 (A,B,XOR);

    always @(*) 
    begin
        case (OP)
            2'b00: // Addition 
                begin 
                    result = R_ADD; 
                end
            2'b01: // OR_XOR_AND
                begin 
                    result = XOR;
                end
            default: 
                begin
                    result = 6'b000000;  
                end
        endcase
    end
    assign R = result;
    assign alu_flag = (result > 6'b0);
endmodule

HDL codes/controller.v
module controller 
( 
    input wire clk, reset, start, 
    input wire [5:0] a, b, 
    input wire [1:0] op, 

    input wire [5:0] alu_out, 
    input wire alu_flag, 
    output wire [5:0] alu_in1, alu_in2, 
    output wire [1:0] alu_op, 

    output reg [5:0] result, 
    output reg flag 
); 

reg [2:0] pstate, nstate; 

parameter [2:0] START = 3'b000, 
                ONE = 3'b001, 
                TWO = 3'b010, 
                THREE = 3'b011, 
                FINISH = 3'b100; 

//Memory 
always @(posedge clk, posedge reset) 
begin : PSR 
    if (reset) 
    begin
        pstate <= START; 
    end
    else 
    begin
        pstate <= nstate; 
    end
end 

//Next State Logic 
always @(*) 
begin: NSOL 
    // Monitor output 
    if(pstate == START)
        $monitor("pstate = START -> clk = %b, reset = %b, start = %b, a = %d, b = %d, op = %b, result = %d, flag = %b\n************************************\n", clk, reset, start, a, b, op, result, flag);
    else if(pstate == ONE)
        $monitor("pstate = ONE -> clk = %b, reset = %b, start = %b, a = %d, b = %d, op = %b, result = %d, flag = %b\n************************************\n", clk, reset, start, a, b, op, result, flag);
    else if(pstate == TWO)
        $monitor("pstate = TWO -> clk = %b, reset = %b, start = %b, a = %d, b = %d, op = %b, result = %d, flag = %b\n************************************\n", clk, reset, start, a, b, op, result, flag);
    else if(pstate == THREE)
        $monitor("pstate = THREE -> clk = %b, reset = %b, start = %b, a = %d, b = %d, op = %b, result = %d, flag = %b\n************************************\n", clk, reset, start, a, b, op, result, flag);
    else if(pstate == FINISH)
        $monitor("pstate = FINISH -> clk = %b, reset = %b, start = %b, a = %d, b = %d, op = %b, result = %d, flag = %b\n************************************\n", clk, reset, start, a, b, op, result, flag);

    nstate = pstate;

    // Next State Logic and Output Logic
    begin: NSL
    case (pstate) 
        START: 
        begin 
            if (start) 
                nstate = ONE; 
        end 

        ONE: 
        begin 
            nstate = TWO; 
        end 

        TWO: 
        begin 
            nstate = THREE; 
        end 

        THREE: 
        begin 
            nstate = FINISH; 
        end 

        FINISH: 
        begin 
            nstate = FINISH; 
        end 

        default: 
            nstate = START; 
    endcase 
end
    result = 6'b000000;
    flag = 1'b0;
begin: OL
    case (pstate) 
        START: 
        begin 
            result = 6'b0;
            flag = 0; 
        end 

        ONE: 
        begin 
            result = alu_out; 
            flag = alu_flag;   
        end 

        TWO: 
        begin 
            result = alu_out; 
            flag = alu_flag;  
        end 

        THREE: 
        begin 
            result = alu_out; 
            flag = alu_flag;  
        end 

        FINISH: 
        begin 
            result = alu_out; 
            flag = alu_flag; 
        end 
        default: 
            nstate = START; 
    endcase 
end
end

assign alu_in1 = a;
assign alu_in2 = b;
assign alu_op = op;

endmodule

HDL codes/top.v
module top
(
    input wire clk, reset, start,
    input wire [5:0] a, b,
    input wire [1:0] op,
    output wire [5:0] result,
    output wire flag
);

wire [5:0] alu_in1, alu_in2;
wire [1:0] alu_op;
wire [5:0] alu_out;
wire alu_flag;

controller controller1
(
    .clk(clk),
    .reset(reset),
    .start(start),
    .a(a),
    .b(b),
    .op(op),
    .alu_in1(alu_in1),
    .alu_in2(alu_in2),
    .alu_op(alu_op),
    .alu_out(alu_out),
    .alu_flag(alu_flag),
    .result(result),
    .flag(flag)
);

ALU datapath1
(
    .A(alu_in1),
    .B(alu_in2),
    .OP(alu_op),
    .R(alu_out),
    .alu_flag(alu_flag)
);

endmodule

HDL codes/top_tb.sv
`timescale 1ns/1ns

module top_tb;

reg clk, reset, start;
reg [5:0] a, b;
reg [1:0] op;
wire [5:0] result;
wire flag;

top top1
(
    .clk(clk),
    .reset(reset),
    .start(start),
    .a(a),
    .b(b),
    .op(op),
    .result(result),
    .flag(flag)
);

initial begin
    clk = 0;
    forever #5 clk = ~clk;  // Toggle clk every 5 time units
end

initial begin
    $dumpfile("top_test.vcd");
    $dumpvars(0, top_tb);

    clk <= 0;
    reset <= 0;
    start <= 0;
    a <= 0;
    b <= 0;
    op <= 0;

    @(negedge clk);
    reset <= 1;

    @(negedge clk);
    reset <= 0;
    start <= 1;
    a <= 5;
    b <= 3;
    op <= 2'b00; // Addition: 5 + 3 = 8 (flag = 1)
    #15;

    a <= 0;
    b <= 0;
    op <= 2'b00; // Addition: 0 + 0 = 0 (flag = 0)
    #10;

    a <= 10;
    b <= 7;
    op <= 2'b01; // OR_XOR_AND: (10 | 7) ^ (10 & 7) = 15 ^ 2 = 13 (flag = 1)
    #20;

    reset <= 1;
    #30;

    $finish();
end

endmodule

HDL codes/alu_test.vcd
$date
	Fri Jun 13 05:53:43 2025
$end
$version
	Icarus Verilog
$end
$timescale
	1ns
$end
$scope module top_tb $end
$var wire 6 ! result [5:0] $end
$var wire 1 " flag $end
$var reg 6 # a [5:0] $end
$var reg 6 $ b [5:0] $end
$var reg 1 % clk $end
$var reg 2 & op [1:0] $end
$var reg 1 ' reset $end
$var reg 1 ( start $end
$scope module top1 $end
$var wire 6 ) a [5:0] $end
$var wire 6 * b [5:0] $end
$var wire 1 % clk $end
$var wire 2 + op [1:0] $end
$var wire 1 ' reset $end
$var wire 1 ( start $end
$var wire 6 , result [5:0] $end
$var wire 1 " flag $end
$var wire 6 - alu_out [5:0] $end
$var wire 2 . alu_op [1:0] $end
$var wire 6 / alu_in2 [5:0] $end
$var wire 6 0 alu_in1 [5:0] $end
$var wire 1 1 alu_flag $end
$scope module controller1 $end
$var wire 6 2 a [5:0] $end
$var wire 6 3 alu_in1 [5:0] $end
$var wire 6 4 alu_in2 [5:0] $end
$var wire 2 5 alu_op [1:0] $end
$var wire 6 6 b [5:0] $end
$var wire 1 % clk $end
$var wire 2 7 op [1:0] $end
$var wire 1 ' reset $end
$var wire 1 ( start $end
$var wire 6 8 alu_out [5:0] $end
$var wire 1 1 alu_flag $end
$var parameter 3 9 FINISH $end
$var parameter 3 : ONE $end
$var parameter 3 ; START $end
$var parameter 3 < THREE $end
$var parameter 3 = TWO $end
$var reg 1 " flag $end
$var reg 3 > nstate [2:0] $end
$var reg 3 ? pstate [2:0] $end
$var reg 6 @ result [5:0] $end
$scope begin NSOL $end
$scope begin NSL $end
$upscope $end
$scope begin OL $end
$upscope $end
$upscope $end
$scope begin PSR $end
$upscope $end
$upscope $end
$scope module datapath1 $end
$var wire 6 A A [5:0] $end
$var wire 6 B B [5:0] $end
$var wire 2 C OP [1:0] $end
$var wire 6 D R [5:0] $end
$var wire 1 1 alu_flag $end
$var wire 6 E XOR [5:0] $end
$var wire 6 F R_ADD [5:0] $end
$var wire 1 G CF_ADD $end
$var reg 6 H result [5:0] $end
$scope module ADD_SUB1 $end
$var wire 6 I A [5:0] $end
$var wire 6 J B [5:0] $end
$var wire 6 K R [5:0] $end
$var wire 1 G CF $end
$upscope $end
$scope module OR_XOR_AND1 $end
$var wire 6 L A [5:0] $end
$var wire 6 M B [5:0] $end
$var wire 6 N R [5:0] $end
$upscope $end
$upscope $end
$upscope $end
$upscope $end
$enddefinitions $end
$comment Show the parameter values. $end
$dumpall
b10 =
b11 <
b0 ;
b1 :
b100 9
$end
#0
$dumpvars
b0 N
b0 M
b0 L
b0 K
b0 J
b0 I
b0 H
0G
b0 F
b0 E
b0 D
b0 C
b0 B
b0 A
bx @
bx ?
b0 >
b0 8
b0 7
b0 6
b0 5
b0 4
b0 3
b0 2
01
b0 0
b0 /
b0 .
b0 -
bx ,
b0 +
b0 *
b0 )
0(
0'
b0 &
0%
b0 $
b0 #
x"
bx !
$end
#5
0"
b0 !
b0 ,
b0 @
b0 ?
b0 >
1%
#10
1'
0%
#15
1%
#20
11
b1000 -
b1000 8
b1000 D
b1000 H
b110 E
b110 N
b1000 F
b1000 K
b1 >
b11 /
b11 4
b11 B
b11 J
b11 M
b11 $
b11 *
b11 6
b101 0
b101 3
b101 A
b101 I
b101 L
b101 #
b101 )
b101 2
1(
0'
0%
#25
1"
b1000 !
b1000 ,
b1000 @
b1 ?
b10 >
1%
#30
b10 >
0%
#35
b10 ?
b11 >
1%
#40
0"
b0 !
b0 ,
b0 @
01
b0 -
b0 8
b0 D
b0 H
b0 E
b0 N
b0 F
b0 K
b0 /
b0 4
b0 B
b0 J
b0 M
b0 $
b0 *
b0 6
b0 0
b0 3
b0 A
b0 I
b0 L
b0 #
b0 )
b0 2
b11 >
0%
#45
b11 ?
b100 >
1%
#50
b100 >
0%
#55
b100 ?
b100 >
1%
#60
1"
b1101 !
b1101 ,
b1101 @
11
b1101 -
b1101 8
b1101 D
b1101 H
b1101 E
b1101 N
b10001 F
b10001 K
b1 .
b1 5
b1 C
b1 &
b1 +
b1 7
b111 /
b111 4
b111 B
b111 J
b111 M
b111 $
b111 *
b111 6
b1010 0
b1010 3
b1010 A
b1010 I
b1010 L
b1010 #
b1010 )
b1010 2
0%
