HDL codes/controller.v
module controller 
( 
    input wire clk, reset, start, 
    input wire [5:0] a, b, 
    input wire [1:0] op, 

    input wire [5:0] alu_out, 
    input wire alu_flag, 
    output wire [5:0] alu_in1, alu_in2, 
    output wire [1:0] alu_op, 

    output reg [5:0] result, 
    output reg flag 
); 

reg [2:0] pstate, nstate; 

parameter [2:0] START = 3'b000, 
                ONE = 3'b001, 
                TWO = 3'b010, 
                THREE = 3'b011, 
                FINISH = 3'b100; 

//Memory 
always @(posedge clk, posedge reset) 
begin : PSR 
    if (reset) 
    begin
        pstate <= START; 
    end
    else 
    begin
        pstate <= nstate; 
    end
end 

//Next State Logic 
always @(*) 
begin: NSOL 
    // Monitor output 
    if(pstate == START)
        $monitor("pstate = START -> clk = %b, reset = %b, start = %b, a = %d, b = %d, op = %b, result = %d, flag = %b\n************************************\n", clk, reset, start, a, b, op, result, flag);
    else if(pstate == ONE)
        $monitor("pstate = ONE -> clk = %b, reset = %b, start = %b, a = %d, b = %d, op = %b, result = %d, flag = %b\n************************************\n", clk, reset, start, a, b, op, result, flag);
    else if(pstate == TWO)
        $monitor("pstate = TWO -> clk = %b, reset = %b, start = %b, a = %d, b = %d, op = %b, result = %d, flag = %b\n************************************\n", clk, reset, start, a, b, op, result, flag);
    else if(pstate == THREE)
        $monitor("pstate = THREE -> clk = %b, reset = %b, start = %b, a = %d, b = %d, op = %b, result = %d, flag = %b\n************************************\n", clk, reset, start, a, b, op, result, flag);
    else if(pstate == FINISH)
        $monitor("pstate = FINISH -> clk = %b, reset = %b, start = %b, a = %d, b = %d, op = %b, result = %d, flag = %b\n************************************\n", clk, reset, start, a, b, op, result, flag);

    nstate = pstate;

    // Next State Logic and Output Logic
    begin: NSL
    case (pstate) 
        START: 
        begin 
            if (start) 
                nstate = ONE; 
        end 

        ONE: 
        begin 
            nstate = TWO; 
        end 

        TWO: 
        begin 
            nstate = THREE; 
        end 

        THREE: 
        begin 
            nstate = FINISH; 
        end 

        FINISH: 
        begin 
            nstate = FINISH; 
        end 

        default: 
            nstate = START; 
    endcase 
end
    result = 6'b000000;
    flag = 1'b0;
begin: OL
    case (pstate) 
        START: 
        begin 
            result = 6'b0;
            flag = 0; 
        end 

        ONE: 
        begin 
            result = alu_out; 
            flag = alu_flag;   
        end 

        TWO: 
        begin 
            result = alu_out; 
            flag = alu_flag;  
        end 

        THREE: 
        begin 
            result = alu_out; 
            flag = alu_flag;  
        end 

        FINISH: 
        begin 
            result = alu_out; 
            flag = alu_flag; 
        end 
        default: 
            nstate = START; 
    endcase 
end
end

assign alu_in1 = a;
assign alu_in2 = b;
assign alu_op = op;

endmodule

HDL codes/controller_tb.v
`timescale 1ns/1ns

module controller_tb;
    reg clk;
    reg reset;
    reg start;
    reg [5:0] a;
    reg [5:0] b;
    reg [1:0] op;
    reg [5:0] alu_out;
    reg alu_flag;
    wire [5:0] alu_in1;
    wire [5:0] alu_in2;
    wire [1:0] alu_op;
    wire [5:0] result;
    wire flag;

    controller dut (
        .clk(clk),
        .reset(reset),
        .start(start),
        .a(a),
        .b(b),
        .op(op),
        .alu_out(alu_out),
        .alu_flag(alu_flag),
        .alu_in1(alu_in1),
        .alu_in2(alu_in2),
        .alu_op(alu_op),
        .result(result),
        .flag(flag)
    );

    initial begin
        clk = 0;
        forever #5 clk = ~clk;
    end

    // Stimulus
    initial begin
        
        reset = 0;
        start = 0;
        a = 6'd0;
        b = 6'd0;
        op = 2'b00;
        alu_out = 6'd0;
        alu_flag = 0;

        
        #10;
        reset = 1;

        
        #10;
        reset = 0;
        start = 1;
        a = 6'd5;
        b = 6'd3;
        op = 2'b00;
        alu_out = 6'd8;  // Addition: 5 + 3
        alu_flag = 1;

        
        #15;
        a = 6'd0;
        b = 6'd0;
        op = 2'b00;
        alu_out = 6'd0;  // Addition: 0 + 0
        alu_flag = 0;

        
        #10;
        a = 6'd10;
        b = 6'd7;
        op = 2'b01;
        alu_out = 6'd13; // OR_XOR_AND: (10 | 7) ^ (10 & 7) = 15 ^ 2 = 13
        alu_flag = 1;

        
        #20;
        $finish;
    end

    
    initial begin
        $monitor("Time=%0t | clk=%b | reset=%b | start=%b | a=%d | b=%d | op=%b | alu_out=%d | alu_flag=%b | alu_in1=%d | alu_in2=%d | alu_op=%b | result=%d | flag=%b",
                 $time, clk, reset, start, a, b, op, alu_out, alu_flag, alu_in1, alu_in2, alu_op, result, flag);
    end

    
    initial begin
        $dumpfile("controller_tb.vcd");
        $dumpvars(0, controller_tb);
    end

endmodule

HDL codes/controller_tb.vcd
$date
	Fri Jun 13 10:01:13 2025
$end
$version
	Icarus Verilog
$end
$timescale
	1ns
$end
$scope module controller_tb $end
$var wire 6 ! result [5:0] $end
$var wire 1 " flag $end
$var wire 2 # alu_op [1:0] $end
$var wire 6 $ alu_in2 [5:0] $end
$var wire 6 % alu_in1 [5:0] $end
$var reg 6 & a [5:0] $end
$var reg 1 ' alu_flag $end
$var reg 6 ( alu_out [5:0] $end
$var reg 6 ) b [5:0] $end
$var reg 1 * clk $end
$var reg 2 + op [1:0] $end
$var reg 1 , reset $end
$var reg 1 - start $end
$scope module dut $end
$var wire 6 . a [5:0] $end
$var wire 1 ' alu_flag $end
$var wire 6 / alu_in1 [5:0] $end
$var wire 6 0 alu_in2 [5:0] $end
$var wire 2 1 alu_op [1:0] $end
$var wire 6 2 alu_out [5:0] $end
$var wire 6 3 b [5:0] $end
$var wire 1 * clk $end
$var wire 2 4 op [1:0] $end
$var wire 1 , reset $end
$var wire 1 - start $end
$var parameter 3 5 FINISH $end
$var parameter 3 6 ONE $end
$var parameter 3 7 START $end
$var parameter 3 8 THREE $end
$var parameter 3 9 TWO $end
$var reg 1 " flag $end
$var reg 3 : nstate [2:0] $end
$var reg 3 ; pstate [2:0] $end
$var reg 6 < result [5:0] $end
$scope begin NSOL $end
$scope begin NSL $end
$upscope $end
$scope begin OL $end
$upscope $end
$upscope $end
$scope begin PSR $end
$upscope $end
$upscope $end
$upscope $end
$enddefinitions $end
$comment Show the parameter values. $end
$dumpall
b10 9
b11 8
b0 7
b1 6
b100 5
$end
#0
$dumpvars
b0 <
bx ;
b0 :
b0 4
b0 3
b0 2
b0 1
b0 0
b0 /
b0 .
0-
0,
b0 +
0*
b0 )
b0 (
0'
b0 &
b0 %
b0 $
b0 #
0"
b0 !
$end
#5
b0 ;
b0 :
1*
#10
0*
1,
#15
1*
#20
b1 :
0*
1'
b1000 (
b1000 2
b11 $
b11 0
b11 )
b11 3
b101 %
b101 /
b101 &
b101 .
1-
0,
#25
1"
b1000 !
b1000 <
b1 ;
b10 :
1*
#30
1"
b1000 !
b1000 <
b10 :
0*
#35
b10 ;
0"
b0 !
b0 <
b11 :
1*
0'
b0 (
b0 2
b0 $
b0 0
b0 )
b0 3
b0 %
b0 /
b0 &
b0 .
#40
b11 :
0*
#45
b11 ;
1"
b1101 !
b1101 <
b100 :
1*
1'
b1101 (
b1101 2
b1 #
b1 1
b1 +
b1 4
b111 $
b111 0
b111 )
b111 3
b1010 %
b1010 /
b1010 &
b1010 .
#50
1"
b1101 !
b1101 <
b100 :
0*
#55
b100 ;
1"
b1101 !
b1101 <
b100 :
1*
#60
1"
b1101 !
b1101 <
0*
